ksef/__init__.py
ksef/client.py
ksef/constants.py
ksef/exceptions.py
ksef/py.typed
ksef/utils.py
ksef/xml_converters.py
ksef/auth/__init__.py
ksef/auth/base.py
ksef/auth/init_session_token_request.py
ksef/auth/token.py
ksef/models/__init__.py
ksef/models/invoice.py
ksef/models/invoice_annotations.py
ksef/models/invoice_rows.py
ksef/models/responses/__init__.py
ksef/models/responses/authorization_challenge.py
ksef/models/responses/authorization_token.py
ksef-0.1.1.dist-info/METADATA
ksef-0.1.1.dist-info/WHEEL
ksef-0.1.1.dist-info/RECORD
