Metadata-Version: 2.4
Name: ksef
Version: 0.1.1
Summary: Python interface for the KSEF API
Project-URL: Repository, https://github.com/samupl/python-ksef
Author-email: Jakub Szafrański <kontakt@samu.pl>
Requires-Python: ~=3.9
Requires-Dist: cryptography>=46.0.2
Requires-Dist: pydantic<2,>=1.10.5
Requires-Dist: requests<3,>=2.28.2
